{
  "task_id": "TSK-P2-GOV-CONV-015",
  "git_sha": "21534c1335d0676131e9becbcb6003acd60599a1",
  "timestamp_utc": "2026-05-03T18:57:33Z",
  "status": "PASS",
  "checks": [
    "pre_ci_admissibility_call:PASS",
    "ci_workflow_admissibility:PASS",
    "evidence_path_wired:PASS",
    "verifier_script_exists:PASS",
    "ci_failure_detection:PASS"
  ],
  "ci_wiring_verified": true,
  "evidence_path_validated": true,
  "summary": {
    "total_checks": 5,
    "passed_checks": 5,
    "failed_checks": 0
  }
}
