{
  "task_id": "TSK-P2-W6-REM-16b",
  "git_sha": "d805b3814d01834ad3783eb13f6427508d731d7f",
  "timestamp_utc": "2026-04-25T06:51:41Z",
  "status": "PASS",
  "metrics": {
    "pre_merge_count": 48,
    "post_merge_count": 49
  },
  "renumbering_decisions": [
    {
      "original_code": "P7601",
      "new_code": "P7504",
      "subsystem": "hardening",
      "justification": "P7601 namespace awarded to Wave 6 Policy Authority per Architect ruling. Hardening trigger evicted to P7504."
    }
  ],
  "drift_check": "PASS"
}
